odoo/addons/mis_builder_demo/README.rst
odoo/addons/mis_builder_demo/__init__.py
odoo/addons/mis_builder_demo/__manifest__.py
odoo/addons/mis_builder_demo/data/mis_budget.xml
odoo/addons/mis_builder_demo/data/mis_report.xml
odoo/addons/mis_builder_demo/data/mis_report_instance.xml
odoo/addons/mis_builder_demo/data/mis_report_style.xml
odoo/addons/mis_builder_demo/i18n/ca.po
odoo/addons/mis_builder_demo/i18n/de.po
odoo/addons/mis_builder_demo/i18n/es.po
odoo/addons/mis_builder_demo/i18n/fr.po
odoo/addons/mis_builder_demo/i18n/hr_HR.po
odoo/addons/mis_builder_demo/i18n/mis_builder_demo.pot
odoo/addons/mis_builder_demo/i18n/nl.po
odoo/addons/mis_builder_demo/i18n/nl_NL.po
odoo/addons/mis_builder_demo/i18n/pt.po
odoo/addons/mis_builder_demo/i18n/pt_BR.po
odoo/addons/mis_builder_demo/models/__init__.py
odoo/addons/mis_builder_demo/models/mis_committed_purchase.py
odoo/addons/mis_builder_demo/models/mis_committed_purchase.sql
odoo/addons/mis_builder_demo/readme/CONTRIBUTORS.rst
odoo/addons/mis_builder_demo/readme/DESCRIPTION.rst
odoo/addons/mis_builder_demo/readme/HISTORY.rst
odoo/addons/mis_builder_demo/readme/ROADMAP.rst
odoo/addons/mis_builder_demo/readme/USAGE.rst
odoo/addons/mis_builder_demo/readme/newsfragments/.gitignore
odoo/addons/mis_builder_demo/security/mis_committed_purchase.xml
odoo/addons/mis_builder_demo/static/description/icon.png
odoo/addons/mis_builder_demo/static/description/index.html
odoo/addons/mis_builder_demo/views/mis_committed_purchase.xml
odoo14_addon_mis_builder_demo-14.0.3.1.3.dist-info/METADATA
odoo14_addon_mis_builder_demo-14.0.3.1.3.dist-info/WHEEL
odoo14_addon_mis_builder_demo-14.0.3.1.3.dist-info/top_level.txt
odoo14_addon_mis_builder_demo-14.0.3.1.3.dist-info/RECORD
