Metadata-Version: 2.1
Name: odoo14-addon-mis-builder-demo
Version: 14.0.3.1.3
Summary: Demo addon for MIS Builder
Home-page: https://github.com/OCA/mis-builder
Author: ACSONE SA/NV, Odoo Community Association (OCA)
Author-email: support@odoo-community.org
License: AGPL-3
Platform: UNKNOWN
Classifier: Programming Language :: Python
Classifier: Framework :: Odoo
Classifier: License :: OSI Approved :: GNU Affero General Public License v3
Classifier: Development Status :: 3 - Alpha
Requires-Python: >=3.6
Requires-Dist: odoo14-addon-mis-builder-budget
Requires-Dist: odoo (<14.1dev,>=14.0a)
